toctoc_controller_router_sdk/__init__.py
toctoc_controller_router_sdk/api_client.py
toctoc_controller_router_sdk/api_response.py
toctoc_controller_router_sdk/configuration.py
toctoc_controller_router_sdk/exceptions.py
toctoc_controller_router_sdk/py.typed
toctoc_controller_router_sdk/rest.py
toctoc_controller_router_sdk/api/__init__.py
toctoc_controller_router_sdk/api/appraisal_api.py
toctoc_controller_router_sdk/api/environment_api.py
toctoc_controller_router_sdk/api/highlight_api.py
toctoc_controller_router_sdk/api/properties_api.py
toctoc_controller_router_sdk/models/__init__.py
toctoc_controller_router_sdk/models/appraisal200_response.py
toctoc_controller_router_sdk/models/appraisal_input_dto.py
toctoc_controller_router_sdk/models/flow_dto.py
toctoc_controller_router_sdk/models/get_communes200_response.py
toctoc_controller_router_sdk/models/get_properties200_response.py
toctoc_controller_router_sdk/models/get_regions200_response.py
toctoc_controller_router_sdk/models/highlight200_response.py
toctoc_controller_router_sdk/models/images.py
toctoc_controller_router_sdk/models/product_usage_dto.py
toctoc_controller_router_sdk/models/properties_address.py
toctoc_controller_router_sdk/models/properties_address_location.py
toctoc_controller_router_sdk/models/properties_area.py
toctoc_controller_router_sdk/models/properties_client.py
toctoc_controller_router_sdk/models/properties_commune.py
toctoc_controller_router_sdk/models/properties_distribution.py
toctoc_controller_router_sdk/models/properties_finances.py
toctoc_controller_router_sdk/models/properties_multimedia.py
toctoc_controller_router_sdk/models/properties_operation.py
toctoc_controller_router_sdk/models/remove200_response.py
toctoc_controller_router_sdk/models/response_appraisal_dto.py
toctoc_controller_router_sdk/models/response_bad_request_dto.py
toctoc_controller_router_sdk/models/response_commune_dto.py
toctoc_controller_router_sdk/models/response_error_dto.py
toctoc_controller_router_sdk-0.0.38.dist-info/METADATA
toctoc_controller_router_sdk-0.0.38.dist-info/WHEEL
toctoc_controller_router_sdk-0.0.38.dist-info/top_level.txt
toctoc_controller_router_sdk-0.0.38.dist-info/RECORD
